.gitignore
.gitmodules
Dockerfile
LICENSE
README.md
requirements.txt
setup.py
detorch/MPI.py
detorch/__init__.py
detorch/config.py
detorch/de.py
detorch/utils.py
detorch.egg-info/PKG-INFO
detorch.egg-info/SOURCES.txt
detorch.egg-info/dependency_links.txt
detorch.egg-info/requires.txt
detorch.egg-info/top_level.txt
detorch/dataclass_config/__init__.py
detorch/dataclass_config/dataclass_config.py
examples/ackley.py
examples/example.py
examples/modules.py
examples/test_problems.py