Metadata-Version: 2.1
Name: detorch
Version: 1.2.1
Summary: Minimal PyTorch Library for Differential Evolution
Home-page: https://github.com/goktug97/de-torch
Author: Göktuğ Karakaşlı
Author-email: karakasligk@gmail.com
License: MIT
Platform: UNKNOWN
Classifier: Programming Language :: Python :: 3
Classifier: License :: OSI Approved :: MIT License
Requires-Python: >=3.7
License-File: LICENSE
